llm_predictive_router/__init__.py
llm_predictive_router/router.py
llm_predictive_router-0.2.1.dist-info/METADATA
llm_predictive_router-0.2.1.dist-info/WHEEL
llm_predictive_router-0.2.1.dist-info/top_level.txt
llm_predictive_router-0.2.1.dist-info/RECORD
