Metadata-Version: 2.1
Name: llm-predictive-router
Version: 0.2.1
Summary: A package to route chat requests between LLMs based on prompt classification
Home-page: https://github.com/csabakecskemeti/llm_predictive_router_package
Author: Csaba Kecskemeti - devquasar.com
Requires-Python: >=3.7
Requires-Dist: torch >=1.9.0
Requires-Dist: transformers >=4.0.0
Requires-Dist: openai
Requires-Dist: datasets
